gw2api/__init__.py
gw2api/events.py
gw2api/guild.py
gw2api/items.py
gw2api/map.py
gw2api/misc.py
gw2api/mumble.py
gw2api/skins.py
gw2api/util.py
gw2api/wvw.py
gw2api/v2/__init__.py
gw2api/v2/account.py
gw2api/v2/achievements.py
gw2api/v2/endpoint.py
gw2api/v2/pvp.py
gw2api/v2/recipes.py
gw2api/v2/transactions.py
gw2api/v2/util.py
gw2api/v2/wvw.py
gw2api-1.1.4.dist-info/DESCRIPTION.rst
gw2api-1.1.4.dist-info/METADATA
gw2api-1.1.4.dist-info/RECORD
gw2api-1.1.4.dist-info/WHEEL
gw2api-1.1.4.dist-info/metadata.json
gw2api-1.1.4.dist-info/pbr.json
gw2api-1.1.4.dist-info/top_level.txt
