Metadata-Version: 2.0
Name: gw2api
Version: 1.1.4
Summary: Guild Wars 2 API
Home-page: https://github.com/hackedd/gw2api
Author: Paul Hooijenga
Author-email: paulhooijenga@gmail.com
License: MIT
Platform: UNKNOWN
Classifier: Development Status :: 3 - Alpha
Classifier: Environment :: Console
Classifier: Environment :: Web Environment
Classifier: Intended Audience :: Developers
Classifier: License :: OSI Approved :: MIT License
Classifier: Operating System :: OS Independent
Classifier: Programming Language :: Python
Classifier: Topic :: Games/Entertainment
Requires-Dist: requests
Requires-Dist: six
